IntelliMaint/__init__.py
IntelliMaint/__version__.py
IntelliMaint/anomaly_detection.py
IntelliMaint/basemonitor.py
IntelliMaint/cli.py
IntelliMaint/component_template.py
IntelliMaint/data_acquisition.py
IntelliMaint/data_analysis.py
IntelliMaint/feature_engineering.py
IntelliMaint/feature_selection.py
IntelliMaint/health_indicator.py
IntelliMaint/intelliMaint_core.py
IntelliMaint/rul_estimation.py
IntelliMaint/signal_processing.py
IntelliMaint/utils.py
grand/__init__.py
grand/_version.py
grand/conformal.py
grand/utils.py
grand/datasets/__init__.py
grand/datasets/data_loader.py
grand/group_anomaly/__init__.py
grand/group_anomaly/group_anomaly.py
grand/group_anomaly/peer_grouping.py
grand/group_anomaly/transformer.py
grand/individual_anomaly/__init__.py
grand/individual_anomaly/individual_anomaly_inductive.py
grand/individual_anomaly/individual_anomaly_transductive.py
intellimaint-1.0.3.dist-info/METADATA
intellimaint-1.0.3.dist-info/WHEEL
intellimaint-1.0.3.dist-info/entry_points.txt
intellimaint-1.0.3.dist-info/top_level.txt
intellimaint-1.0.3.dist-info/RECORD
