Metadata-Version: 2.4
Name: IntelliMaint
Version: 1.0.3
Summary: A prognostics package by IntelliPredikt Technologies
Author: IPTLP0032
Author-email: iptgithub@intellipredikt.com
Requires-Python: >=3.12
Requires-Dist: scikit-learn
Requires-Dist: GPy
Requires-Dist: minisom
Requires-Dist: scipy>=1.3.0
Requires-Dist: matplotlib
Requires-Dist: numpy<2.0.0,>=1.7
Requires-Dist: mplcursors
Requires-Dist: fpdf2
Requires-Dist: tensorflow<2.20,>=2.10
Requires-Dist: keras>=2.10
Requires-Dist: pandas
Requires-Dist: seaborn
Requires-Dist: imbalanced-learn
Requires-Dist: tqdm
Requires-Dist: paho-mqtt
Requires-Dist: statsmodels
Requires-Dist: requests
Requires-Dist: streamlit
Dynamic: author
Dynamic: author-email
Dynamic: description
Dynamic: description-content-type
Dynamic: requires-dist
Dynamic: requires-python
Dynamic: summary
